aliyunsdkdfs/__init__.py
aliyunsdkdfs/request/__init__.py
aliyunsdkdfs/request/v20180620/AttachVscMountPointRequest.py
aliyunsdkdfs/request/v20180620/BindVscMountPointAliasRequest.py
aliyunsdkdfs/request/v20180620/CreateAccessGroupRequest.py
aliyunsdkdfs/request/v20180620/CreateAccessRuleRequest.py
aliyunsdkdfs/request/v20180620/CreateFileSystemRequest.py
aliyunsdkdfs/request/v20180620/CreateMountPointRequest.py
aliyunsdkdfs/request/v20180620/CreateQosPolicyRequest.py
aliyunsdkdfs/request/v20180620/CreateUserGroupsMappingRequest.py
aliyunsdkdfs/request/v20180620/CreateVscMountPointRequest.py
aliyunsdkdfs/request/v20180620/DeleteAccessGroupRequest.py
aliyunsdkdfs/request/v20180620/DeleteAccessRuleRequest.py
aliyunsdkdfs/request/v20180620/DeleteFileSystemRequest.py
aliyunsdkdfs/request/v20180620/DeleteMountPointRequest.py
aliyunsdkdfs/request/v20180620/DeleteQosPolicyRequest.py
aliyunsdkdfs/request/v20180620/DeleteUserGroupsMappingRequest.py
aliyunsdkdfs/request/v20180620/DeleteVscMountPointRequest.py
aliyunsdkdfs/request/v20180620/DescribeRegionsRequest.py
aliyunsdkdfs/request/v20180620/DescribeVscMountPointsRequest.py
aliyunsdkdfs/request/v20180620/DetachVscMountPointRequest.py
aliyunsdkdfs/request/v20180620/GetAccessGroupRequest.py
aliyunsdkdfs/request/v20180620/GetAccessRuleRequest.py
aliyunsdkdfs/request/v20180620/GetFileSystemRequest.py
aliyunsdkdfs/request/v20180620/GetMountPointRequest.py
aliyunsdkdfs/request/v20180620/GetRegionRequest.py
aliyunsdkdfs/request/v20180620/ListAccessGroupsRequest.py
aliyunsdkdfs/request/v20180620/ListAccessRulesRequest.py
aliyunsdkdfs/request/v20180620/ListFederationsRequest.py
aliyunsdkdfs/request/v20180620/ListFileSystemsRequest.py
aliyunsdkdfs/request/v20180620/ListMountPointsRequest.py
aliyunsdkdfs/request/v20180620/ListQosPoliciesRequest.py
aliyunsdkdfs/request/v20180620/ListUserGroupsMappingsRequest.py
aliyunsdkdfs/request/v20180620/ModifyAccessGroupRequest.py
aliyunsdkdfs/request/v20180620/ModifyAccessRuleRequest.py
aliyun_python_sdk_dfs-0.0.2.dist-info/LICENSE
aliyun_python_sdk_dfs-0.0.2.dist-info/METADATA
aliyun_python_sdk_dfs-0.0.2.dist-info/WHEEL
aliyun_python_sdk_dfs-0.0.2.dist-info/top_level.txt
aliyun_python_sdk_dfs-0.0.2.dist-info/RECORD
